oathldap_tool/__about__.py
oathldap_tool/__init__.py
oathldap_tool/base.py
oathldap_tool/cli.py
oathldap_tool/decpin.py
oathldap_tool/genkey.py
oathldap_tool/ldap.py
oathldap_tool/py.typed
oathldap_tool/ykadd.py
oathldap_tool/ykcheck.py
oathldap_tool/ykinfo.py
oathldap_tool/ykinit.py
oathldap_tool/ykreset.py
oathldap_tool/yubikey.py
oathldap_tool/__pycache__/__about__.cpython-38.opt-1.pyc
oathldap_tool/__pycache__/__init__.cpython-38.opt-1.pyc
oathldap_tool/__pycache__/base.cpython-38.opt-1.pyc
oathldap_tool/__pycache__/cli.cpython-38.opt-1.pyc
oathldap_tool/__pycache__/decpin.cpython-38.opt-1.pyc
oathldap_tool/__pycache__/genkey.cpython-38.opt-1.pyc
oathldap_tool/__pycache__/ldap.cpython-38.opt-1.pyc
oathldap_tool/__pycache__/ykadd.cpython-38.opt-1.pyc
oathldap_tool/__pycache__/ykcheck.cpython-38.opt-1.pyc
oathldap_tool/__pycache__/ykinfo.cpython-38.opt-1.pyc
oathldap_tool/__pycache__/ykinit.cpython-38.opt-1.pyc
oathldap_tool/__pycache__/ykreset.cpython-38.opt-1.pyc
oathldap_tool/__pycache__/yubikey.cpython-38.opt-1.pyc
oath_ldap_tool-1.3.4.dist-info/LICENSE
oath_ldap_tool-1.3.4.dist-info/METADATA
oath_ldap_tool-1.3.4.dist-info/WHEEL
oath_ldap_tool-1.3.4.dist-info/entry_points.txt
oath_ldap_tool-1.3.4.dist-info/top_level.txt
oath_ldap_tool-1.3.4.dist-info/RECORD
